[
    {
        "id": "67123490a9712",
        "username": "tung.bui2004lk",
        "name": "B\u00f9i Thanh T\u00f9ng",
        "user_img_path": "..\/assets\/images\/user_avatar\/51ab1979.png",
        "content": "a",
        "image": "",
        "time": "5:12 PM - Oct 18, 2024",
        "react": 0,
        "comment": 0,
        "bookmark": 0,
        "share": 0,
        "react_action": 0,
        "bookmark_action": 0
    },
    {
        "id": "6712355909847",
        "username": "tung.bui2004lk",
        "name": "B\u00f9i Thanh T\u00f9ng",
        "user_img_path": "..\/assets\/images\/user_avatar\/51ab1979.png",
        "content": "b",
        "image": "",
        "time": "5:15 PM - Oct 18, 2024",
        "react": 0,
        "comment": 0,
        "bookmark": 0,
        "share": 0,
        "react_action": 0,
        "bookmark_action": 0
    },
    {
        "id": "6712355be00a2",
        "username": "tung.bui2004lk",
        "name": "B\u00f9i Thanh T\u00f9ng",
        "user_img_path": "..\/assets\/images\/user_avatar\/51ab1979.png",
        "content": "c",
        "image": "",
        "time": "5:15 PM - Oct 18, 2024",
        "react": 1,
        "comment": 0,
        "bookmark": 0,
        "share": 0,
        "react_action": 1,
        "bookmark_action": 0
    }
]